adsbxcot/__init__.py
adsbxcot/classes.py
adsbxcot/commands.py
adsbxcot/constants.py
adsbxcot/functions.py
adsbxcot-7.0.0.dist-info/LICENSE
adsbxcot-7.0.0.dist-info/METADATA
adsbxcot-7.0.0.dist-info/WHEEL
adsbxcot-7.0.0.dist-info/entry_points.txt
adsbxcot-7.0.0.dist-info/top_level.txt
adsbxcot-7.0.0.dist-info/RECORD
