Metadata-Version: 2.2
Name: adsbxcot
Version: 7.0.0
Summary: Display Aircraft in TAK. A gateway for displaying aircraft tracks from ADS-B Aggregators (ADSBExchange, adsb.fi, et al.) in TAK Products (ATAK, WinTAK, iTAK, TAK Server, TAKX).
Home-page: https://github.com/snstac/adsbxcot
Maintainer: Greg Albrecht <oss@undef.net>
Maintainer-email: oss@undef.net
License: Apache 2
Project-URL: CI: GitHub Actions, https://github.com/snstac/adsbxcot/actions
Project-URL: GitHub: issues, https://github.com/snstac/adsbxcot/issues
Project-URL: GitHub: repo, https://github.com/snstac/adsbxcot
Project-URL: Docs: Changelog, https://adsbxcot.readthedocs.io/en/latest/changelog/
Project-URL: Docs: RTD, https://adsbxcot.rtfd.io
Keywords: Cursor on Target,CoT,ATAK,TAK,WinTAK,TAK,TAK Server,ADS-B,Aircraft,ADSB,UAT
Classifier: License :: OSI Approved :: Apache Software License
Classifier: Intended Audience :: Developers
Classifier: Programming Language :: Python
Classifier: Programming Language :: Python :: 3
Classifier: Programming Language :: Python :: 3 :: Only
Classifier: Programming Language :: Python :: 3.7
Classifier: Programming Language :: Python :: 3.8
Classifier: Programming Language :: Python :: 3.9
Classifier: Programming Language :: Python :: 3.10
Classifier: Programming Language :: Python :: 3.11
Classifier: Development Status :: 5 - Production/Stable
Classifier: Operating System :: POSIX
Classifier: Operating System :: MacOS :: MacOS X
Classifier: Operating System :: Microsoft :: Windows
Classifier: Operating System :: OS Independent
Requires-Python: <4,>=3.7
License-File: LICENSE
Requires-Dist: pytak>=6.2.0
Requires-Dist: aircot>=1.2.0
Requires-Dist: aiohttp
Provides-Extra: test
Requires-Dist: pytest-asyncio; extra == "test"
Requires-Dist: pytest-cov; extra == "test"
Requires-Dist: pylint; extra == "test"
Requires-Dist: flake8; extra == "test"
Requires-Dist: black; extra == "test"
